Metadata-Version: 2.1
Name: edotools
Version: 0.1.2
Summary: AutoML
Home-page: UNKNOWN
Author-email: edvard88@inbox.ru
License: UNKNOWN
Platform: UNKNOWN
